deep_rewire/__init__.py
deep_rewire/convert.py
deep_rewire/converter.py
deep_rewire/optim.py
deep_rewire/optimizer.py
deep_rewire/utils.py
deep_rewire-1.0.5.dist-info/LICENSE
deep_rewire-1.0.5.dist-info/METADATA
deep_rewire-1.0.5.dist-info/WHEEL
deep_rewire-1.0.5.dist-info/top_level.txt
deep_rewire-1.0.5.dist-info/RECORD
