Metadata-Version: 2.1
Name: deep_rewire
Version: 1.0.5
Summary: DeepRewire is a PyTorch-based project designed to simplify the creation and optimization of sparse neural networks with the concepts from the [Deep Rewiring](https://arxiv.org/abs/1711.05136) paper by Bellec et. al. ⚠️ Note: The implementation is not made by any of the authors. Please double-check everything before use.
Home-page: https://github.com/LuggiStruggi/DeepRewire
Author: Lukas König
Author-email: luggistruggi@gmail.com
Classifier: Programming Language :: Python :: 3
Classifier: License :: OSI Approved :: MIT License
Classifier: Operating System :: OS Independent
Requires-Python: >=3.6
License-File: LICENSE
Requires-Dist: torch
